vijil_dome/Dome.py
vijil_dome/__init__.py
vijil_dome/defaults.py
vijil_dome/detectors/__init__.py
vijil_dome/detectors/methods/__init__.py
vijil_dome/detectors/methods/configs/banlists/default_banlist.txt
vijil_dome/detectors/methods/configs/embedding_files/jailbreak/garak_inthewild_jailbreak.raw.txt
vijil_dome/detectors/methods/configs/presidio/default_config.yaml
vijil_dome/detectors/methods/embedding_models.py
vijil_dome/detectors/methods/encoding_heuristics.py
vijil_dome/detectors/methods/factcheck_roberta.py
vijil_dome/detectors/methods/flashtext_kw_banlist.py
vijil_dome/detectors/methods/hhem_hallucination.py
vijil_dome/detectors/methods/jb_perplexity_heuristics.py
vijil_dome/detectors/methods/llm_models.py
vijil_dome/detectors/methods/openai_models.py
vijil_dome/detectors/methods/perspective.py
vijil_dome/detectors/methods/pi_hf_deberta.py
vijil_dome/detectors/methods/pi_hf_mbert.py
vijil_dome/detectors/methods/pii_presidio.py
vijil_dome/detectors/methods/secret_detector.py
vijil_dome/detectors/methods/toxicity_deberta.py
vijil_dome/detectors/utils/__init__.py
vijil_dome/detectors/utils/embeddings_base.py
vijil_dome/detectors/utils/hf_model.py
vijil_dome/detectors/utils/llm_api_base.py
vijil_dome/detectors/utils/prompt_templates/modifiable_prompts.py
vijil_dome/embeds/__init__.py
vijil_dome/embeds/embedder.py
vijil_dome/embeds/examples.py
vijil_dome/embeds/index/__init__.py
vijil_dome/embeds/index/basic.py
vijil_dome/embeds/models/__init__.py
vijil_dome/embeds/models/fastembed.py
vijil_dome/embeds/models/sentence_transformers.py
vijil_dome/guardrails/__init__.py
vijil_dome/guardrails/config_parser.py
vijil_dome/guardrails/defaults.py
vijil_dome/guardrails/examples/ex_guarded_chat_completions.py
vijil_dome/guardrails/instrumentation/instrumentation.py
vijil_dome/guardrails/instrumentation/metrics.py
vijil_dome/instrumentation/examples/ex_guardrail.py
vijil_dome/instrumentation/examples/ex_logging.ipynb
vijil_dome/instrumentation/examples/ex_tracing.py
vijil_dome-1.3.3.dist-info/METADATA
vijil_dome-1.3.3.dist-info/WHEEL
vijil_dome-1.3.3.dist-info/licenses/LICENSE
vijil_dome-1.3.3.dist-info/RECORD
