Metadata-Version: 2.4
Name: vijil-dome
Version: 1.3.3
Summary: 
License-File: LICENSE
Author: Pradeep Das
Author-email: pradeep@vijil.ai
Requires-Python: >=3.11,<3.14
Classifier: Programming Language :: Python :: 3
Classifier: Programming Language :: Python :: 3.11
Classifier: Programming Language :: Python :: 3.12
Classifier: Programming Language :: Python :: 3.13
Provides-Extra: embeddings
Provides-Extra: google
Provides-Extra: langchain
Provides-Extra: opentelemetry
Requires-Dist: annoy (>=1.17.3,<2.0.0) ; extra == "embeddings"
Requires-Dist: detect-secrets (>=1.5.0,<2.0.0)
Requires-Dist: fastmcp (>=2.13.1,<3.0.0)
Requires-Dist: flashtext (>=2.7,<3.0)
Requires-Dist: google-api-python-client (>=2.176.0,<3.0.0) ; extra == "google"
Requires-Dist: grpcio (>=1.73.1,<2.0.0)
Requires-Dist: huggingface-hub (>=0.33.2,<0.34.0)
Requires-Dist: litellm (>=1.74.0.post1,<2.0.0)
Requires-Dist: mcp (>=1.21.2,<2.0.0)
Requires-Dist: nest-asyncio (>=1.6.0,<2.0.0)
Requires-Dist: numpy (>=1.26.4,<2.0.0)
Requires-Dist: openai (>=1.93.2,<2.0.0)
Requires-Dist: opentelemetry-api (>=1.34.1,<2.0.0) ; extra == "opentelemetry"
Requires-Dist: opentelemetry-exporter-gcp-monitoring (>=1.9.0a0,<2.0.0) ; extra == "opentelemetry"
Requires-Dist: opentelemetry-exporter-gcp-trace (>=1.9.0,<2.0.0) ; extra == "opentelemetry"
Requires-Dist: opentelemetry-exporter-otlp (>=1.34.1,<2.0.0) ; extra == "opentelemetry"
Requires-Dist: opentelemetry-exporter-otlp-proto-common (>=1.34.1,<2.0.0) ; extra == "opentelemetry"
Requires-Dist: opentelemetry-exporter-otlp-proto-grpc (>=1.34.1,<2.0.0) ; extra == "opentelemetry"
Requires-Dist: opentelemetry-exporter-otlp-proto-http (>=1.34.1,<2.0.0) ; extra == "opentelemetry"
Requires-Dist: opentelemetry-instrumentation (>=0.55b1,<0.56) ; extra == "opentelemetry"
Requires-Dist: opentelemetry-instrumentation-asyncio (>=0.55b1,<0.56) ; extra == "opentelemetry"
Requires-Dist: opentelemetry-instrumentation-logging (>=0.55b1,<0.56) ; extra == "opentelemetry"
Requires-Dist: opentelemetry-instrumentation-threading (>=0.55b1,<0.56) ; extra == "opentelemetry"
Requires-Dist: opentelemetry-propagator-gcp (>=1.9.0,<2.0.0) ; extra == "opentelemetry"
Requires-Dist: opentelemetry-proto (>=1.34.1,<2.0.0) ; extra == "opentelemetry"
Requires-Dist: opentelemetry-resourcedetector-gcp (>=1.9.0a0,<2.0.0) ; extra == "opentelemetry"
Requires-Dist: opentelemetry-sdk (>=1.34.1,<2.0.0) ; extra == "opentelemetry"
Requires-Dist: opentelemetry-semantic-conventions (>=0.55b1,<0.56) ; extra == "opentelemetry"
Requires-Dist: pandas (>=2.3.1,<3.0.0)
Requires-Dist: presidio_analyzer (>=2.2.358,<3.0.0)
Requires-Dist: presidio_anonymizer (>=2.2.358,<3.0.0)
Requires-Dist: pydantic (>=2.11.7,<3.0.0)
Requires-Dist: pytest (>=8.4.1,<9.0.0)
Requires-Dist: pytest-asyncio (>=1.0.0,<2.0.0)
Requires-Dist: python-dotenv (>=1.1.1,<2.0.0)
Requires-Dist: scipy (>=1.16.0,<2.0.0)
Requires-Dist: sentence-transformers (>=5.0.0,<6.0.0)
Requires-Dist: toml (>=0.10.2,<0.11.0)
Requires-Dist: torch (>=2.8.0,<3.0.0)
Requires-Dist: tqdm (>=4.67.1,<5.0.0)
Requires-Dist: transformers (>=4.53.1,<5.0.0)
